{
  "name": "AI21 Jamba 1.5 Large",
  "org": "AI21 Labs",
  "family": "AI21 Jamba",
  "releaseDate": "2024-08-22",
  "status": "released",
  "openness": "open-weights",
  "license": "Jamba Open Model License",
  "paramsB": 398,
  "activeParamsB": 94,
  "archClass": "hybrid",
  "archDisplay": "Hybrid Mamba-Transformer MoE (Jamba)",
  "ctxK": 256,
  "modalities": [
    "text"
  ],
  "langCount": 9,
  "capabilities": {
    "reasoning": false,
    "coding": true,
    "vision": false,
    "functionCalling": true,
    "toolUse": true,
    "agentic": true
  },
  "apiAvailable": true,
  "price": {
    "input": 2,
    "output": 8,
    "provider": "AI21 Studio"
  },
  "links": {
    "hf": "ai21labs/AI21-Jamba-Large-1.5",
    "docs": "docs.ai21.com"
  },
  "note": "Flagship open hybrid SSM-Transformer MoE, 94B/398B active/total, RULER-verified 256K context, function calling and JSON output.",
  "quants": [
    "GGUF Q4"
  ],
  "vramQ4Gb": 240.4,
  "vramFp16Gb": 796,
  "tps4090": null,
  "tpsNote": "Too large to run on a single RTX 4090 even at Q4; requires multi-GPU or CPU offload.",
  "effortLabel": null,
  "isDefaultConfig": true,
  "isBestConfig": true,
  "specSources": {
    "paramsB": "https://huggingface.co/ai21labs/AI21-Jamba-Large-1.5",
    "ctxK": "https://www.ai21.com/blog/announcing-jamba-model-family/",
    "releaseDate": "https://www.ai21.com/blog/announcing-jamba-model-family/",
    "openness": "https://huggingface.co/ai21labs/AI21-Jamba-Large-1.5"
  },
  "results": [
    {
      "benchmarkSlug": "mmlu",
      "score": 80,
      "source": "self-reported",
      "sourceUrl": "https://arxiv.org/html/2408.12570v1"
    },
    {
      "benchmarkSlug": "mmlu-pro",
      "score": 48.3,
      "source": "self-reported",
      "sourceUrl": "https://arxiv.org/html/2408.12570v1"
    },
    {
      "benchmarkSlug": "gpqa",
      "score": 36.9,
      "source": "self-reported",
      "sourceUrl": "https://arxiv.org/html/2408.12570v1"
    },
    {
      "benchmarkSlug": "arc-challenge",
      "score": 93,
      "source": "self-reported",
      "sourceUrl": "https://arxiv.org/html/2408.12570v1"
    },
    {
      "benchmarkSlug": "bbh",
      "score": 65.5,
      "source": "self-reported",
      "sourceUrl": "https://arxiv.org/html/2408.12570v1"
    },
    {
      "benchmarkSlug": "humaneval",
      "score": 71.3,
      "source": "self-reported",
      "sourceUrl": "https://arxiv.org/html/2408.12570v1"
    },
    {
      "benchmarkSlug": "gsm8k",
      "score": 87,
      "source": "self-reported",
      "sourceUrl": "https://arxiv.org/html/2408.12570v1"
    },
    {
      "benchmarkSlug": "ifeval",
      "score": 81.5,
      "source": "self-reported",
      "sourceUrl": "https://arxiv.org/html/2408.12570v1"
    },
    {
      "benchmarkSlug": "bfcl",
      "score": 85.5,
      "source": "self-reported",
      "sourceUrl": "https://arxiv.org/html/2408.12570v1",
      "notes": "Berkeley Function-Calling Leaderboard"
    },
    {
      "benchmarkSlug": "arena-hard",
      "score": 65.4,
      "source": "self-reported",
      "sourceUrl": "https://www.ai21.com/blog/announcing-jamba-model-family/",
      "notes": "Arena-Hard"
    },
    {
      "benchmarkSlug": "wildbench",
      "score": 48.5,
      "source": "self-reported",
      "sourceUrl": "https://arxiv.org/html/2408.12570v1",
      "notes": "WildBench score from Table 3 (Chatbot Evaluations) of the Jamba-1.5 technical report, alongside the Arena-Hard 65.4 already in the corpus."
    },
    {
      "benchmarkSlug": "truthfulqa",
      "score": 58.3,
      "source": "self-reported",
      "sourceUrl": "https://arxiv.org/html/2408.12570v1",
      "notes": "0-shot TruthfulQA score from Table 2 (Academic Benchmarks) of the Jamba-1.5 technical report."
    }
  ],
  "verificationNotes": "Confirmed via HF model card ai21labs/AI21-Jamba-Large-1.5 (94B active/398B total, Jamba Open Model License permitting commercial use, 256K context, 9 languages: English, Spanish, French, Portuguese, Italian, Dutch, German, Arabic, Hebrew) and ai21.com/blog/announcing-jamba-model-family/ (published 2024-08-22, 256K effective context, Arena-Hard 65.4 for Large matching the arena result row). All 9 arxiv-sourced benchmark rows (MMLU 80, MMLU-Pro 48.3, GPQA 36.9, ARC-Challenge 93, BBH 65.5, HumanEval 71.3, GSM8K 87, IFEval 81.5, BFCL 85.5) plus RULER 95.7 were fetched directly from arxiv.org/html/2408.12570v1 Tables 2/4 and match exactly. $2/$8 per-million-token pricing corroborated by independent pricing aggregators. All fields left unchanged."
}
